AUTHORS.txt
LICENSE
MANIFEST.in
README.md
requirements.txt
setup.py
cmsplugin_contact_plus/__init__.py
cmsplugin_contact_plus/actions.py
cmsplugin_contact_plus/admin.py
cmsplugin_contact_plus/apps.py
cmsplugin_contact_plus/checks.py
cmsplugin_contact_plus/cms_plugins.py
cmsplugin_contact_plus/forms.py
cmsplugin_contact_plus/local_settings.py
cmsplugin_contact_plus/models.py
cmsplugin_contact_plus/signals.py
cmsplugin_contact_plus/utils.py
cmsplugin_contact_plus.egg-info/PKG-INFO
cmsplugin_contact_plus.egg-info/SOURCES.txt
cmsplugin_contact_plus.egg-info/dependency_links.txt
cmsplugin_contact_plus.egg-info/requires.txt
cmsplugin_contact_plus.egg-info/top_level.txt
cmsplugin_contact_plus/locale/es/LC_MESSAGES/django.mo
cmsplugin_contact_plus/locale/es/LC_MESSAGES/django.po
cmsplugin_contact_plus/locale/fr/LC_MESSAGES/django.mo
cmsplugin_contact_plus/locale/fr/LC_MESSAGES/django.po
cmsplugin_contact_plus/migrations/0001_initial.py
cmsplugin_contact_plus/migrations/0002_auto_20151013_1157.py
cmsplugin_contact_plus/migrations/0003_auto_20161102_1927.py
cmsplugin_contact_plus/migrations/0004_auto_20170410_1553.py
cmsplugin_contact_plus/migrations/__init__.py
cmsplugin_contact_plus/south_migrations/__init__.py
cmsplugin_contact_plus/templates/cmsplugin_contact_plus/change_form.html
cmsplugin_contact_plus/templates/cmsplugin_contact_plus/contact.html
cmsplugin_contact_plus/templates/cmsplugin_contact_plus/email.txt