Metadata-Version: 1.1
Name: cmsplugin-contact-plus
Version: 1.3.11
Summary: A django CMS plugin to dynamically create contact forms.
Home-page: https://github.com/arteria/cmsplugin-contact-plus/
Author: arteria GmbH
Author-email: admin@arteria.ch
License: BSD License
Platform: UNKNOWN
Classifier: Development Status :: 5 - Production/Stable
Classifier: Environment :: Web Environment
Classifier: Intended Audience :: Developers
Classifier: License :: OSI Approved :: BSD License
Classifier: Operating System :: OS Independent
Classifier: Programming Language :: Python
Classifier: Programming Language :: Python :: 2.7
Classifier: Framework :: Django
